src/__init__.py
src/jobs/__init__.py
src/jobs/bronze/__init__.py
src/jobs/bronze/bronze.py
src/jobs/bronze/entrypoint.py
src/params.py
src/schemas/bronze_schema.py
prt_databricks_simplify_7da_data_ingest-0.1.0.dist-info/LICENSE
prt_databricks_simplify_7da_data_ingest-0.1.0.dist-info/METADATA
prt_databricks_simplify_7da_data_ingest-0.1.0.dist-info/WHEEL
prt_databricks_simplify_7da_data_ingest-0.1.0.dist-info/RECORD
