Metadata-Version: 2.1
Name: prt-databricks-simplify-7da-data-ingest
Version: 0.1.0
Summary: providing creating data layers from pdro s3 buckets
Home-page: https://github.com/enverus-pr/prt-databricks-simplify-7da-data-ingest
Author: Zdenek Hruby
Author-email: 144209297+Zdenek-Hruby-Enverus@users.noreply.github.com
Requires-Python: >=3.10,<4.0
Classifier: Programming Language :: Python :: 3
Classifier: Programming Language :: Python :: 3.10
Classifier: Programming Language :: Python :: 3.11
Requires-Dist: ba-spark-utils (==1.0.0)
Requires-Dist: confluent-kafka (>=1.4.2)
Requires-Dist: delta-spark (>=2.4.0)
Requires-Dist: elm-utils (>=1.0.11,<2.0.0)
Requires-Dist: fsspec (>=2023.4.0,<2024.0.0)
Requires-Dist: psycopg (>=3.1.9,<4.0.0)
Requires-Dist: psycopg-binary (>=3.1.9,<4.0.0)
Requires-Dist: pyspark (>=3.5.0,<4.0.0)
Requires-Dist: pyyaml (>=6.0,<7.0)
Requires-Dist: s3fs (>=2023.4.0,<2024.0.0)
Project-URL: Repository, https://github.com/enverus-pr/prt-databricks-simplify-7da-data-ingest
